Workbook
Name DetailedCapShares: #REF!
Name IntermediateCapShares: #REF!
Name IQ_CH: 110000
Name IQ_CQ: 5000
Name IQ_CY: 10000
Name IQ_DAILY: 500000
Name IQ_FH: 100000
Name IQ_FQ: 500
Name IQ_FY: 1000
Name IQ_LTM: 2000
Name IQ_MONTH: 15000
Name IQ_NTM: 6000
Name IQ_WEEK: 50000
Name IQ_YTD: 3000
Name SummaryCapTableFullyDilutedShares: #REF!

Sheet Task I >>>
B6: Financial Model - Zoom Viewer (Case Study)

Sheet Financial Model
B2: Zoom Viewer - Case Study
B4: Remarks & Assumptions - PLEASE READ FIRST
B5: General: Zoom Viewer, located in Berlin, Germany, is a leading technology company offering a communications technology Software based on a Software-as-a-Service (SaaS) subscription model with long-term subscriptions ranging between 12 to 60 months. The software provides mainly videotelephony and online chat services through a cloud-based peer-to-peer software platform. In course of the Covid-19 pandemic, the Company experienced a surge in demand for their product as the solutions transcend geographical distance and allow problems to be identified, examined, and solved immediately and, more importantly, remotely to prevent the spread of the so called SARS-CoV-2 Virus. Due to its high "product stickiness" and its ability to constantly respond to customer demands as well as its stable connection, Zoom Viewer has developed to one of the leading Technology companies in that sector. In addition to that, from an environmental perspective, the solutions help the environment by, amongst other factors, saved travels and hence a reduction of CO2 emissions. Task: Zoom Viewer generally has one core revenue stream from offering their software on a subscription model ("Subscription"). Revenue generated from subscription are accrued pro rata based on the contract duraction. In order to implement the software and activate additional modules and services, upon customer request, the Company recognizes revenue under "Maintenance". For certain customers, additional seminars are offered as well as technical consultancy services which are recorded under "Service". The latter is not material and has a fairly low margin as it is a requested service add-on by certain customers. As Zoom Viewer has experienced substantial growth, the Investment Bank, Silverman Blacks, approached the Company if they are open for potential discussions on the sale of the company. In order to get a first impression on the valuation of the Company the CEO, Tiger Tyson, (holding 100% of the shares) approached you to calculate the enterprise value of Zoom Viewer under high-level assumptions using a DCF-approach and validate the valuation quickly using both a Revenue/EV and EBITDA/EV multiple (see tab "Multiples competitors"). In the past couple of days, you have prepared a bottom-up revenue plan by customer (very unusual but due to the constant customer base as a result of the stickiness of the product and the high subscription periods a fairly reasonable approach). Your plan to kick-off the valuation is to structure the revenue data by customer (see Tab "Revenue by customer") in the format as laid out in the template by revenue stream and year (yellow highlighted cells in rows 18-20). Please note that the CEO, Tiger Tyson, is known for his spontaneous choleric attacks if he detects errors in the financials. As he has a particular focus on the revenue figures per segment (and knows these by heart), make sure that they are definitely correct.
B8: Additional information on the assumptions:
B9: 1. The company is entirely financed with equity. There is no debt and no corresponding interest payments
B10: 2. NOL refers to "Net Operating Losses". These are cumulated operating losses from prior to 2020 that can be carried forward and can offset future years operating gains for tax purposes
B11: 3. The Terminal Growth Rate is 2%.
B12: 4. The Weighted Average Costs of Capital (WACC) are 10%.
B13: 5. The Change in NWC refers to the cash effect, e.g. a positive value indicates that there is a positive cash flow from changes in NWC.
B14: 6. For the multiple valuation, use the financials (Revenue and EBITDA) for the first plan year- 2022e. | K14: Malte Bieber
B15: Income Statement | F15: 1 | G15: 2 | H15: 3 | I15: 4 | J15: 5
B16: in USD millions | D16: 2020 | E16: =D16+1 -> 2021 | F16: =E16+1 -> 2022 | G16: =F16+1 -> 2023 | H16: =G16+1 -> 2024 | I16: =H16+1 -> 2025 | J16: =I16+1 -> 2026 | K16: CAGR '21-'26
B17: Revenue
B18: Subscription | D18: 177.36678 | E18: =+SUMIFS('Revenue by customer'!$E$4:$E$239,'Revenue by customer'!$D$4:$D$239, E$16, 'Revenue by customer'!$C$4:$C$239, $B18)/1000000 -> 154.55598 | F18: =+SUMIFS('Revenue by customer'!$E$4:$E$239,'Revenue by customer'!$D$4:$D$239, F$16, 'Revenue by customer'!$C$4:$C$239, $B18)/1000000 -> 239.67516 | G18: =+SUMIFS('Revenue by customer'!$E$4:$E$239,'Revenue by customer'!$D$4:$D$239, G$16, 'Revenue by customer'!$C$4:$C$239, $B18)/1000000 -> 242.40296 | H18: =+SUMIFS('Revenue by customer'!$E$4:$E$239,'Revenue by customer'!$D$4:$D$239, H$16, 'Revenue by customer'!$C$4:$C$239, $B18)/1000000 -> 200.26754 | I18: =+SUMIFS('Revenue by customer'!$E$4:$E$239,'Revenue by customer'!$D$4:$D$239, I$16, 'Revenue by customer'!$C$4:$C$239, $B18)/1000000 -> 320.53259 | J18: =+SUMIFS('Revenue by customer'!$E$4:$E$239,'Revenue by customer'!$D$4:$D$239, J$16, 'Revenue by customer'!$C$4:$C$239, $B18)/1000000 -> 308.72929 | K18: =(J18/D18)^(1/6) -1 -> 0.096775127
B19: Maintenance | D19: 28.36355 | E19: =+SUMIFS('Revenue by customer'!$E$4:$E$239,'Revenue by customer'!$D$4:$D$239, E$16, 'Revenue by customer'!$C$4:$C$239, $B19)/1000000 -> 71.524742 | F19: =+SUMIFS('Revenue by customer'!$E$4:$E$239,'Revenue by customer'!$D$4:$D$239, F$16, 'Revenue by customer'!$C$4:$C$239, $B19)/1000000 -> 35.56452 | G19: =+SUMIFS('Revenue by customer'!$E$4:$E$239,'Revenue by customer'!$D$4:$D$239, G$16, 'Revenue by customer'!$C$4:$C$239, $B19)/1000000 -> 32.447258 | H19: =+SUMIFS('Revenue by customer'!$E$4:$E$239,'Revenue by customer'!$D$4:$D$239, H$16, 'Revenue by customer'!$C$4:$C$239, $B19)/1000000 -> 68.635893 | I19: =+SUMIFS('Revenue by customer'!$E$4:$E$239,'Revenue by customer'!$D$4:$D$239, I$16, 'Revenue by customer'!$C$4:$C$239, $B19)/1000000 -> 30.542144 | J19: =+SUMIFS('Revenue by customer'!$E$4:$E$239,'Revenue by customer'!$D$4:$D$239, J$16, 'Revenue by customer'!$C$4:$C$239, $B19)/1000000 -> 36.330569 | K19: =(J19/D19)^(1/6) -1 -> 0.042122091
B20: Service | D20: 17.200204 | E20: =+SUMIFS('Revenue by customer'!$E$4:$E$239,'Revenue by customer'!$D$4:$D$239, E$16, 'Revenue by customer'!$C$4:$C$239, $B20)/1000000 -> 19.201624 | F20: =+SUMIFS('Revenue by customer'!$E$4:$E$239,'Revenue by customer'!$D$4:$D$239, F$16, 'Revenue by customer'!$C$4:$C$239, $B20)/1000000 -> 2.355069 | G20: =+SUMIFS('Revenue by customer'!$E$4:$E$239,'Revenue by customer'!$D$4:$D$239, G$16, 'Revenue by customer'!$C$4:$C$239, $B20)/1000000 -> 28.290719 | H20: =+SUMIFS('Revenue by customer'!$E$4:$E$239,'Revenue by customer'!$D$4:$D$239, H$16, 'Revenue by customer'!$C$4:$C$239, $B20)/1000000 -> 76.097008 | I20: =+SUMIFS('Revenue by customer'!$E$4:$E$239,'Revenue by customer'!$D$4:$D$239, I$16, 'Revenue by customer'!$C$4:$C$239, $B20)/1000000 -> 1.139662 | J20: =+SUMIFS('Revenue by customer'!$E$4:$E$239,'Revenue by customer'!$D$4:$D$239, J$16, 'Revenue by customer'!$C$4:$C$239, $B20)/1000000 -> 14.390488 | K20: =(J20/D20)^(1/6) -1 -> -0.029288174
B21: Total Revenue | D21: 222.93053 | E21: =SUM(E18:E20) -> 245.28234 | F21: =SUM(F18:F20) -> 277.59475 | G21: =SUM(G18:G20) -> 303.14094 | H21: =SUM(H18:H20) -> 345.00044 | I21: =SUM(I18:I20) -> 352.2144 | J21: =SUM(J18:J20) -> 359.45035 | K21: =(J21/D21)^(1/6) -1 -> 0.082874746
B22: YoY Growth in % | E22: =(E21/D21)-1 -> 0.10026357 | F22: =(F21/E21)-1 -> 0.13173557 | G22: =(G21/F21)-1 -> 0.092026896 | H22: =(H21/G21)-1 -> 0.13808595 | I22: =(I21/H21)-1 -> 0.020910005 | J22: =(J21/I21)-1 -> 0.020544152
B24: Cost of Goods Sold | D24: =D21-D25 -> 89.172213 | E24: =E21-E25 -> 85.84882 | F24: =F21-F25 -> 83.278426 | G24: =G21-G25 -> 81.848053 | H24: =H21-H25 -> 82.800105 | I24: =I21-I25 -> 77.487168 | J24: =J21-J25 -> 75.484573
B25: Gross Profit | D25: =D21*D26 -> 133.75832 | E25: =E21*E26 -> 159.43352 | F25: =F21*F26 -> 194.31633 | G25: =G21*G26 -> 221.29288 | H25: =H21*H26 -> 262.20033 | I25: =I21*I26 -> 274.72723 | J25: =J21*J26 -> 283.96577
B26: Gross Margin in % | D26: 0.6 | E26: 0.65 | F26: 0.7 | G26: 0.73 | H26: 0.76 | I26: 0.78 | J26: 0.79
B28: Operating Expenses
B29: General & Administrative | D29: -13.475 | E29: -18.375 | F29: -22.96875 | G29: -25.875 | H29: -28.4625 | I29: -30.508242 | J29: -31.118407
B30: Marketing & Sales | D30: -26.95 | E30: -36.75 | F30: -45.9375 | G30: -51.75 | H30: -56.925 | I30: -61.016484 | J30: -62.236814
B31: Research & Development | D31: -13.475 | E31: -18.375 | F31: -22.96875 | G31: -25.875 | H31: -28.4625 | I31: -30.508242 | J31: -31.118407
B32: Total Operating Expenses | D32: =SUM(D29:D31) -> -53.9 | E32: =SUM(E29:E31) -> -73.5 | F32: =SUM(F29:F31) -> -91.875 | G32: =SUM(G29:G31) -> -103.5 | H32: =SUM(H29:H31) -> -113.85 | I32: =SUM(I29:I31) -> -122.03297 | J32: =SUM(J29:J31) -> -124.47363
B34: EBITDA | D34: =D25+D32 -> 79.858319 | E34: =E25+E32 -> 85.933524 | F34: =F25+F32 -> 102.44133 | G34: =G25+G32 -> 117.79288 | H34: =H25+H32 -> 148.35033 | I34: =I25+I32 -> 152.69426 | J34: =J25+J32 -> 159.49215
B35: EBITDA Margin | D35: =D34/D21 -> 0.35822065 | E35: =E34/E21 -> 0.35034533 | F35: =F34/F21 -> 0.36903193 | G35: =G34/G21 -> 0.38857465 | H35: =H34/H21 -> 0.43000042 | I35: =I34/I21 -> 0.43352646 | J35: =J34/J21 -> 0.4437112
B37: Depreciation | D37: =D32*D38 -> -2.695 | E37: =E32*E38 -> -3.675 | F37: =F32*F38 -> -4.59375 | G37: =G32*G38 -> -5.175 | H37: =H32*H38 -> -5.6925 | I37: =I32*I38 -> -6.1016484 | J37: =J32*J38 -> -6.2236814
B38: Depreciation as % of OpEx | D38: 0.05 | E38: 0.05 | F38: 0.05 | G38: 0.05 | H38: 0.05 | I38: 0.05 | J38: 0.05
B39: Amortization | D39: =D32*D40 -> -1.078 | E39: =E32*E40 -> -1.47 | F39: =F32*F40 -> -1.8375 | G39: =G32*G40 -> -2.07 | H39: =H32*H40 -> -2.277 | I39: =I32*I40 -> -2.4406594 | J39: =J32*J40 -> -2.4894726
B40: Amortization as % of OpEx | D40: 0.02 | E40: 0.02 | F40: 0.02 | G40: 0.02 | H40: 0.02 | I40: 0.02 | J40: 0.02
B42: EBIT | D42: =D34+D37+D39 -> 76.085319 | E42: =E34+E37+E39 -> 80.788524 | F42: =F34+F37+F39 -> 96.010077 | G42: =G34+G37+G39 -> 110.54788 | H42: =H34+H37+H39 -> 140.38083 | I42: =I34+I37+I39 -> 144.15196 | J42: =J34+J37+J39 -> 150.77899
B44: Interest | D44: 0 | E44: 0 | F44: 0 | G44: 0 | H44: 0 | I44: 0 | J44: 0
B45: NOL (as of year-end) | C45: 40 | D45: 0 | E45: 0 | F45: 0 | G45: 0 | H45: 0 | I45: 0 | J45: 0
B46: Tax | D46: =-(D42-C45)*D47 -> -14.434128 | E46: =-(E42-D45)*E47 -> -32.315409 | F46: =-(F42-E45)*F47 -> -38.404031 | G46: =-(G42-F45)*G47 -> -44.219153 | H46: =-(H42-G45)*H47 -> -56.152333 | I46: =-(I42-H45)*I47 -> -57.660782 | J46: =-(J42-I45)*J47 -> -60.311596
B47: Tax Rate | D47: =40% -> 0.4 | E47: =40% -> 0.4 | F47: =40% -> 0.4 | G47: =40% -> 0.4 | H47: =40% -> 0.4 | I47: =40% -> 0.4 | J47: =40% -> 0.4
B49: Net Income | D49: =D42+D44+D46 -> 61.651192 | E49: =E42+E44+E46 -> 48.473114 | F49: =F42+F44+F46 -> 57.606046 | G49: =G42+G44+G46 -> 66.32873 | H49: =H42+H44+H46 -> 84.2285 | I49: =I42+I44+I46 -> 86.491173 | J49: =J42+J44+J46 -> 90.467395
B51: Cash Flow Statement
B53: in USD millions | D53: 2020 | E53: =D53+1 -> 2021 | F53: =E53+1 -> 2022 | G53: =F53+1 -> 2023 | H53: =G53+1 -> 2024 | I53: =H53+1 -> 2025 | J53: =I53+1 -> 2026
B54: EBITDA | D54: =D34 -> 79.858319 | E54: =E34 -> 85.933524 | F54: =F34 -> 102.44133 | G54: =G34 -> 117.79288 | H54: =H34 -> 148.35033 | I54: =I34 -> 152.69426 | J54: =J34 -> 159.49215
B55: Change in Net Working Capital (NWC) | D55: 6 | E55: =-(E21-D21)*E56 -> -2.2351812 | F55: =-(F21-E21)*F56 -> -3.2312409 | G55: =-(G21-F21)*G56 -> -2.5546183 | H55: =-(H21-G21)*H56 -> -4.1859503 | I55: =-(I21-H21)*I56 -> -0.7213961 | J55: =-(J21-I21)*J56 -> -0.7235946
B56: NWC Change as % of Revenue Change | D56: 0.1 | E56: 0.1 | F56: 0.1 | G56: 0.1 | H56: 0.1 | I56: 0.1 | J56: 0.1
B57: Taxes | D57: =D46 -> -14.434128 | E57: =E46 -> -32.315409 | F57: =F46 -> -38.404031 | G57: =G46 -> -44.219153 | H57: =H46 -> -56.152333 | I57: =I46 -> -57.660782 | J57: =J46 -> -60.311596
B58: Cash Flow from Operations | D58: =D54+D55+D57 -> 71.424192 | E58: =E54+E55+E57 -> 51.382933 | F58: =F54+F55+F57 -> 60.806055 | G58: =G54+G55+G57 -> 71.019112 | H58: =H54+H55+H57 -> 88.01205 | I58: =I54+I55+I57 -> 94.312085 | J58: =J54+J55+J57 -> 98.456954
B60: Capital Expenditures | D60: -5.39 | E60: -7.35 | F60: -8.26875 | G60: -9.315 | H60: -9.108 | I60: -9.7626375 | J60: -8.713154
B61: Cash Flow from Investments | D61: =D60 -> -5.39 | E61: =E60 -> -7.35 | F61: =F60 -> -8.26875 | G61: =G60 -> -9.315 | H61: =H60 -> -9.108 | I61: =I60 -> -9.7626375 | J61: =J60 -> -8.713154
B63: Dividend | D63: -5 | E63: -10 | F63: -15 | G63: -30 | H63: -40 | I63: -100 | J63: -50
B64: Cash Flow from Financing | D64: =D63 -> -5 | E64: =E63 -> -10 | F64: =F63 -> -15 | G64: =G63 -> -30 | H64: =H63 -> -40 | I64: =I63 -> -100 | J64: =J63 -> -50
B66: Change in Cash & Cash Equivalents | D66: =D58+D61+D64 -> 61.034192 | E66: =E58+E61+E64 -> 34.032933 | F66: =F58+F61+F64 -> 37.537305 | G66: =G58+G61+G64 -> 31.704112 | H66: =H58+H61+H64 -> 38.90405 | I66: =I58+I61+I64 -> -15.450553 | J66: =J58+J61+J64 -> 39.7438
B68: Enterprise Value Calculation
B70: in USD millions | D70: 2020 | E70: =D70+1 -> 2021 | F70: =E70+1 -> 2022 | G70: =F70+1 -> 2023 | H70: =G70+1 -> 2024 | I70: =H70+1 -> 2025 | J70: =I70+1 -> 2026
B71: Unlevered Free Cash Flows to the Firm | D71: =D34-D55+D46 -> 59.424192 | E71: =E34-E55+E46 -> 55.853295 | F71: =F34-F55+F46 -> 67.268537 | G71: =G34-G55+G46 -> 76.128348 | H71: =H34-H55+H46 -> 96.38395 | I71: =I34-I55+I46 -> 95.754877 | J71: =J34-J55+J46 -> 99.904143
B73: Assumptions
B74: Terminal Growth Rate | C74: 0.02
B75: WACC | C75: 0.1
B78: Enterprise Value (2022-2026) | C78: =NPV(C75, F71:J71) -> 323.91838
B79: Terminal Value | C79: =((J71*(1+C74))/(C75-C74))/((1+C75)^4) -> 870.0074
B80: Enterprise Value | C80: =SUM(C78:C79) -> 1193.9258
B82: Revenue multiple | C82: ='Multiples competitors'!G13 -> 3.7
B83: Revenue | C83: =F21 -> 277.59475
B84: Enterprise Value | C84: =+C82*C83 -> 1027.1006
B86: EBITDA multiple | C86: ='Multiples competitors'!J13 -> 10.3
B87: EBITDA | C87: =F34 -> 102.44133
B88: Enterprise Value | C88: =+C86*C87 -> 1055.1457

Sheet Sources for Task I >>>

Sheet Revenue by customer
B3: Customer Name | C3: Revenue type | D3: Year | E3: Revenue in USD | K3: 2020 | L3: =K3+1 -> 2021 | M3: =L3+1 -> 2022 | N3: =M3+1 -> 2023 | O3: =N3+1 -> 2024 | P3: =O3+1 -> 2025 | Q3: =P3+1 -> 2026
B4: 1100 - Adams Place | C4: Maintenance | D4: 2020 | E4: 1944315 | H4: Total Revenue (in USDm) | K4: =+SUMIF($D$4:$D$239,K3,$E$4:$E$239)/1000000 -> 222.93053 | L4: =+SUMIF($D$4:$D$239,L3,$E$4:$E$239)/1000000 -> 245.28234 | M4: =+SUMIF($D$4:$D$239,M3,$E$4:$E$239)/1000000 -> 277.59475 | N4: =+SUMIF($D$4:$D$239,N3,$E$4:$E$239)/1000000 -> 303.14094 | O4: =+SUMIF($D$4:$D$239,O3,$E$4:$E$239)/1000000 -> 345.00044 | P4: =+SUMIF($D$4:$D$239,P3,$E$4:$E$239)/1000000 -> 352.2144 | Q4: =+SUMIF($D$4:$D$239,Q3,$E$4:$E$239)/1000000 -> 359.45035
B5: Amerigroup // Anthem (Wellpoint) | C5: Service | D5: 2021 | E5: 1958018
B6: Anka Behavioral Health | C6: Maintenance | D6: 2026 | E6: =38155818-38000000 -> 155818
B7: Arlington TX Management LLC (DBA) Arlington Residence 7 Rehabilitation Center | C7: Subscription | D7: 2020 | E7: 74695402
B8: Aspen Skilled Healthcare | C8: Maintenance | D8: 2021 | E8: 2994670
B9: Balboa Horizons | C9: Service | D9: 2023 | E9: =9046700-9000000 -> 46700
B10: Behavior Analysis Support Services, Inc. | C10: Maintenance | D10: 2026 | E10: 22035
B11: Behavior Change Institute (NM) | C11: Service | D11: 2026 | E11: 137809
B12: Boys and Girls Club of Wetaskiwin | C12: Subscription | D12: 2026 | E12: =38000000+287 -> 38000287
B13: Brookshire Residence and Rehabilitation Center | C13: Service | D13: 2022 | E13: 1155
B14: Call for Help, Inc. | C14: Subscription | D14: 2023 | E14: =6000000+9000000 -> 15000000
B15: Clinica Family Health Services | C15: Maintenance | D15: 2020 | E15: 9
B16: Complete Home Care of the Palm Beaches, LLC | C16: Service | D16: 2022 | E16: 3
B17: Courtyard Residence and Rehabilitation Center | C17: Service | D17: 2023 | E17: 4
B18: Elmhurst Care Center | C18: Subscription | D18: 2021 | E18: 5030000
B19: Enlivant | C19: Subscription | D19: 2021 | E19: 5001002
B20: Ensign Group | C20: Maintenance | D20: 2022 | E20: 0
B21: Exodus Recovery Inc. | C21: Service | D21: 2021 | E21: 10000000
B22: Floresville Residence and Rehabilitation Center | C22: Maintenance | D22: 2025 | E22: =15000000-10000000 -> 5000000
B23: Fox Subacute at Warrington | C23: Maintenance | D23: 2022 | E23: 1335203
B24: Frontier Behavioral Health | C24: Subscription | D24: 2025 | E24: 11558321
B25: Gaymont | C25: Subscription | D25: 2020 | E25: 20467755
B26: Global Healthcare | C26: Subscription | D26: 2025 | E26: 10696362
B27: Greenville Glen | C27: Maintenance | D27: 2024 | E27: 1003990
B28: Hamakua Health Center | C28: Service | D28: 2025 | E28: 943541
B29: Hospice & Palliative CareCenter HQ | C29: Subscription | D29: 2022 | E29: 651791
B30: Hospice of Acadiana, Inc. | C30: Subscription | D30: 2020 | E30: 84764
B31: Junior Blind of America | C31: Subscription | D31: 2024 | E31: =128143+11000000 -> 11128143
B32: Lake Point Nursing - El Dorado | C32: Subscription | D32: 2024 | E32: =22000000+7235 -> 22007235
B33: Lake Point Nursing Center, Augusta | C33: Maintenance | D33: 2026 | E33: 411
B34: LifeShare Management Group, Inc. | C34: Subscription | D34: 2023 | E34: =75000000+386 -> 75000386
B35: Luther Manor (IA) | C35: Maintenance | D35: 2025 | E35: 497
B36: Mansfield Place Assisted Living | C36: Maintenance | D36: 2024 | E36: =22600000-22000000 -> 600000
B37: Medford Leas | C37: Maintenance | D37: 2023 | E37: 4500000
B38: Medical Home Team | C38: Subscription | D38: 2024 | E38: 12000000
B39: Milestone Retirement Communities, LLC. | C39: Subscription | D39: 2023 | E39: 10000000
B40: Oakmont at Gordon Park | C40: Service | D40: 2026 | E40: 3
B41: Participation House Support Services/OneCare Home and Community Support Services | C41: Subscription | D41: 2025 | E41: =10000000-2 -> 9999998
B42: Penn Foundation, Inc | C42: Subscription | D42: 2021 | E42: 1807641
B43: Positive Behavior Support Consulting & Psychological Resources, PC | C43: Subscription | D43: 2026 | E43: 41155725
B44: Preferred Therapy Solutions | C44: Subscription | D44: 2024 | E44: 2787345
B45: Recovery Centers of America | C45: Maintenance | D45: 2023 | E45: 16957753
B46: Rehab Pro | C46: Subscription | D46: 2026 | E46: 78062565
B47: Reliant Care Management Company | C47: Maintenance | D47: 2026 | E47: 14710328
B48: San Juan Counseling Center | C48: Maintenance | D48: 2025 | E48: =11669563-10000000 -> 1669563
B49: Sedgwick Claims Management Services, Inc. | C49: Subscription | D49: 2022 | E49: 3894083
B50: Solution On-Call Services | C50: Maintenance | D50: 2020 | E50: 9234320
B51: Spectrum Health Care LP and affiliated entities | C51: Service | D51: 2023 | E51: 5212809
B52: Spectrum Human Services | C52: Subscription | D52: 2022 | E52: 1357940
B53: Spring Creek Rehabilitation and Health Care Center | C53: Service | D53: 2020 | E53: 293155
B54: St. Joseph Senior Living | C54: Subscription | D54: 2026 | E54: 164851
B55: State of Indiana | C55: Subscription | D55: 2026 | E55: =42000000+38935 -> 42038935
B56: Stockdale Residence and Rehabilitation Center | C56: Subscription | D56: 2020 | E56: 48648
B57: Straight & Narrow, Inc | C57: Maintenance | D57: 2021 | E57: 84472
B58: Telligen | C58: Maintenance | D58: 2026 | E58: 11740
B59: The Arc Of The Central Chesapeake Region | C59: Maintenance | D59: 2023 | E59: 5956
B60: The Spectrum Center for Autism | C60: Subscription | D60: 2022 | E60: -2171
B61: Vernova Healthcare | C61: Service | D61: 2024 | E61: 2959326
B62: Victoria Residence and Rehabilitation Center | C62: Subscription | D62: 2022 | E62: 206546815
B63: VNA Hospice of Philadelphia | C63: Service | D63: 2024 | E63: 3632493
B64: VNAs of Vermont | C64: Subscription | D64: 2026 | E64: 1765797
B65: Wedgwood Christian Services | C65: Maintenance | D65: 2025 | E65: 465265
B66: 1100 - Adams Place | C66: Service | D66: 2023 | E66: 251293
B67: Amerigroup // Anthem (Wellpoint) | C67: Subscription | D67: 2025 | E67: =37000000+1241 -> 37001241
B68: Anka Behavioral Health | C68: Subscription | D68: 2021 | E68: 125000000
B69: Arlington TX Management LLC (DBA) Arlington Residence 7 Rehabilitation Center | C69: Maintenance | D69: 2025 | E69: 982
B70: Aspen Skilled Healthcare | C70: Maintenance | D70: 2024 | E70: =90100000-90000000 -> 100000
B71: Balboa Horizons | C71: Maintenance | D71: 2026 | E71: 278
B72: Behavior Analysis Support Services, Inc. | C72: Subscription | D72: 2022 | E72: 239
B73: Behavior Change Institute (NM) | C73: Maintenance | D73: 2026 | E73: 201
B74: Boys and Girls Club of Wetaskiwin | C74: Maintenance | D74: 2026 | E74: 20
B75: Brookshire Residence and Rehabilitation Center | C75: Subscription | D75: 2025 | E75: =10000000+8 -> 10000008
B76: Call for Help, Inc. | C76: Maintenance | D76: 2023 | E76: 9000000
B77: Clinica Family Health Services | C77: Subscription | D77: 2024 | E77: 6000000
B78: Complete Home Care of the Palm Beaches, LLC | C78: Maintenance | D78: 2025 | E78: 0
B79: Exodus Recovery Inc. | C79: Subscription | D79: 2020 | E79: -0.99999997
B80: Floresville Residence and Rehabilitation Center | C80: Maintenance | D80: 2021 | E80: 3568215
B81: Fox Subacute at Warrington | C81: Subscription | D81: 2026 | E81: 65163712
B82: Frontier Behavioral Health | C82: Maintenance | D82: 2025 | E82: 3903688
B83: Gaymont | C83: Subscription | D83: 2020 | E83: 60621602
B84: Global Healthcare | C84: Maintenance | D84: 2026 | E84: =42437583-42000000 -> 437583
B85: Greenville Glen | C85: Maintenance | D85: 2022 | E85: 12109250
B86: Hamakua Health Center | C86: Maintenance | D86: 2024 | E86: =11316392-11000000 -> 316392
B87: Hospice & Palliative CareCenter HQ | C87: Subscription | D87: 2020 | E87: 1156029
B88: Hospice of Acadiana, Inc. | C88: Maintenance | D88: 2024 | E88: 734195
B89: Junior Blind of America | C89: Subscription | D89: 2024 | E89: =90000000+822322 -> 90822322
B90: Lake Point Nursing - El Dorado | C90: Maintenance | D90: 2020 | E90: 32341
B91: Lake Point Nursing Center, Augusta | C91: Maintenance | D91: 2026 | E91: 179921
B92: LifeShare Management Group, Inc. | C92: Service | D92: 2023 | E92: 6210
B93: Luther Manor (IA) | C93: Maintenance | D93: 2022 | E93: 1728
B94: Mansfield Place Assisted Living | C94: Subscription | D94: 2021 | E94: 759
B95: Medford Leas | C95: Maintenance | D95: 2021 | E95: 41000000
B96: Medical Home Team | C96: Subscription | D96: 2025 | E96: =105464542+242 -> 105464784
B97: Milestone Retirement Communities, LLC. | C97: Subscription | D97: 2023 | E97: 16000000
B98: Oakmont at Gordon Park | C98: Maintenance | D98: 2023 | E98: -16
B99: Participation House Support Services/OneCare Home and Community Support Services | C99: Subscription | D99: 2022 | E99: 4314416
B100: Penn Foundation, Inc | C100: Maintenance | D100: 2025 | E100: 0
B101: Positive Behavior Support Consulting & Psychological Resources, PC | C101: Service | D101: 2023 | E101: =75157630-75000000 -> 157630
B102: Preferred Therapy Solutions | C102: Subscription | D102: 2020 | E102: 568452
...

Sheet Multiples competitors
G3: FV/Revenue | I3: CAGR | J3: FV/EBITDA | L3: CAGR | M3: CY22 EBITDA | N3: P/E | P3: CAGR | Q3: FCF Yield
C4: Company | D4: Share Price | E4: Equity Value | F4: Firm Value | G4: CY2022 | H4: CY2023 | I4: '21-'23 | J4: CY2022 | K4: CY2023 | L4: '21-'23 | M4: Margin | N4: CY2022 | O4: CY2023 | P4: '21-'23 | Q4: CY2022 | R4: CY2023
C5: Competitor I | D5: 18.09 | E5: 1042 | F5: 952 | G5: 3.2 | H5: 3.2 | I5: 0.24 | J5: 9.2 | K5: 6.6 | L5: 0.25 | M5: 0.44 | N5: 15.3 | O5: 11.9 | P5: 0.31 | Q5: 0.02 | R5: -0.01
C6: Competitor II | D6: 59.86 | E6: 10676 | F6: 9615 | G6: 3.5 | H6: 3.4 | I6: 0.2 | J6: 11.3 | K6: 12.3 | L6: 0.24 | M6: 0.38 | N6: 33.5 | Q6: 0.03 | R6: 0.03
C7: Competitor III | D7: 33.9 | E7: 5692 | F7: 4919 | G7: 3.7 | H7: 3.6 | I7: 0.24 | J7: 10 | L7: -0.03 | M7: -0.08 | Q7: -0.02 | R7: 0.03
C8: Competitor III | D8: 82.03 | E8: 2797 | F8: 2585 | G8: 4.9 | H8: 4 | I8: 0.5 | J8: 10.8 | K8: 11.1 | M8: -0.07 | P8: -0.34 | Q8: 0 | R8: 0
C9: Competitor IV | D9: 187.48 | E9: 8813 | F9: 8890 | G9: 3.9 | H9: 4 | I9: 0.28 | J9: 10.3 | M9: 0 | P9: -0.1
C10: Competitor V | D10: 51.5 | E10: 3013 | F10: 2561 | G10: 4.8 | H10: 3.6 | I10: 0.54 | J10: 10.8 | K10: 11.9 | M10: 0.11 | Q10: 0.01 | R10: 0.03
C11: Competitor VI | D11: 2.9 | E11: 604 | F11: 517 | G11: 2.7 | H11: 2.2 | I11: 0.24 | J11: 8.8
C13: Median | G13: =MEDIAN(G5:G11) -> 3.7 | H13: =MEDIAN(H5:H11) -> 3.6 | J13: =MEDIAN(J5:J11) -> 10.3 | K13: =MEDIAN(K5:K11) -> 11.5
C14: Mean | G14: =AVERAGE(G5:G11) -> 3.8142857 | H14: =AVERAGE(H5:H11) -> 3.4285714 | J14: =AVERAGE(J5:J11) -> 10.171429 | K14: =AVERAGE(K5:K11) -> 10.475

Sheet Task II >>>
B6: Top 10 customer - Zoom Viewer buy-side (Case Study)

Sheet Customer Concentration
B2: Multi-Currency Revenue Reporting
B4: Remarks & Tasks - PLEASE READ FIRST
B5: General: The CEO is happy with your calculations however, he expected the worth of his Company to be much higher. In order to achieve his envisaged valuation, Tyson Tiger now plans to acquire a competitor mainly operating in Africa, a region that Zoom Viewer is currently not operating in, to realize synergy effects. His overall goal is to penetrate the African region and realize positive cost effects in order to improve the top-line and the EBITDA of the Company in the next three years before going into a structured sell-side process. Task: Tiger Tyson received a red-flag from BrewWaterHut Users indicating a potential customer concentration (high dependency on certain customers). As the CEO is highly focused on the top-line, he wanted to conduct the analysis by himself upon retrieval of the data. As he does not know how to operate Microsoft Excel, he asked you again for your support since he was pleased with your work on the financial model. Q1: From the notes you have taken during the meeting with Tiger Tyson and BreWaterHut Users, you are supposed to (i) populate the table showing the revenue per top 10 customer using the information from the sheet "Multi-currency order book", (ii) convert the foreign FX to USD to report one consolidated USD revenue figure for 2020 and 2021 to the CEO, (iii) separate the revenue development from FY20 to FY21 in FX and organic effects given significant foreign exchange fluctuations between 2020 and 2021, and (iv) determine the share of the top 10 customer as a % of total revenue and prepare a short answer (no need to be written down) on your opinion on the customer concentration and additional required information to build a qualified answer for Tiger Tyson. With numerous exclamation marks highlighted in bright red you have noted that you should pay attention to the correctness of the values ("checks"). Q2: Please take a position on the following question for a subsequent brief discussion: (i) What is the difference between a SaaS business model compared to a traditional manufacturing business model? Please use the textbox below (Q2) to take high-level bullet points for discussion purposes.
B8: Q1:
B9: Hint: If revenues were EUR 100 in 2020 and EUR 100 in 2021, but EUR/USD fluctuated, then the organic change would
B10: be 0 and all change, when converted to USD, would be FX effect
B12: Customer Order Book | M12: Gesamt-Effekt | N12: =SUM(M33:N33) -> 7603216.7
B13: Currency | C13: FX rate | D13: 2020 | E13: =D13+1 -> 2021 | G13: Country code
B14: USD | C14: USD/USD | D14: 1 | E14: 1 | G14: United States | M14: % Organic Effect | N14: =N33/N12 -> 0.91077452
B15: ZAR | C15: ZAR/USD | D15: 0.06818 | E15: 0.06274 | G15: South Africa
B16: RWF | C16: RWF/USD | D16: 0.001 | E16: 0.00095 | G16: Ruanda | M16: % FX-Effect | N16: =M33/N12 -> 0.089225481
B17: GBP | C17: GBP/USD | D17: 1.3649 | E17: 1.35104 | G17: UK
B19: Hint: If it says GBP/USD is 1.4, that means that for each GBP, you get 1.4 USD.
B21: Top 10 revenue by customer (in local currency) | H21: Top 10 revenue by customer (in USD)
B22: Customer | C22: Currency | D22: 2020 | E22: =D22+1 -> 2021 | H22: Customer | I22: 2020 | J22: =I22+1 -> 2021 | L22: 2020 @ FX20 | M22: FX Effect | N22: Organic Effect
B23: Customer 1 | C23: ZAR | D23: {=+_xlfn.XLOOKUP($B23, 'Multi-currency order book'!$B$7:$B$36, 'Multi-currency order book'!D$7:D$36, FEHLER, 0)} -> 30800821 | E23: {=_xlfn.XLOOKUP($B23, 'Multi-currency order book'!$B$7:$B$36, 'Multi-currency order book'!E$7:E$36, FEHLER, 0)} -> 51004144 | H23: Customer 1 | I23: =D23*_xlfn.XLOOKUP($C23,$B$14:$B$17,D$14:D$17, 0, 0,1) -> 2100000 | J23: =E23*_xlfn.XLOOKUP($C23,$B$14:$B$17,E$14:E$17, 0, 0,1) -> 3200000 | L23: =E23*_xlfn.XLOOKUP($C23,$B$14:$B$17,D$14:D$17, 0, 0,1) -> 3477462.5 | M23: =L23-J23 -> 277462.54 | N23: =J23-I23 -> 1100000
B24: Customer 2 | C24: GBP | D24: {=_xlfn.XLOOKUP($B24, 'Multi-currency order book'!$B$7:$B$36, 'Multi-currency order book'!D$7:D$36, FEHLER, 0)} -> 1465308.8 | E24: {=_xlfn.XLOOKUP($B24, 'Multi-currency order book'!$B$7:$B$36, 'Multi-currency order book'!E$7:E$36, FEHLER, 0)} -> 1554358.1 | H24: Customer 2 | I24: =D24*_xlfn.XLOOKUP($C24,$B$14:$B$17,D$14:D$17, 0, 0,1) -> 2000000 | J24: =E24*_xlfn.XLOOKUP($C24,$B$14:$B$17,E$14:E$17, 0, 0,1) -> 2100000 | L24: =E24*_xlfn.XLOOKUP($C24,$B$14:$B$17,D$14:D$17, 0, 0,1) -> 2121543.4 | M24: =L24-J24 -> 21543.404 | N24: =J24-I24 -> 100000
B25: Customer 3 | C25: RWF | D25: {=_xlfn.XLOOKUP($B25, 'Multi-currency order book'!$B$7:$B$36, 'Multi-currency order book'!D$7:D$36, FEHLER, 0)} -> 1800000000 | E25: {=_xlfn.XLOOKUP($B25, 'Multi-currency order book'!$B$7:$B$36, 'Multi-currency order book'!E$7:E$36, FEHLER, 0)} -> 2.0526316e+09 | H25: Customer 3 | I25: =D25*_xlfn.XLOOKUP($C25,$B$14:$B$17,D$14:D$17, 0, 0,1) -> 1800000 | J25: =E25*_xlfn.XLOOKUP($C25,$B$14:$B$17,E$14:E$17, 0, 0,1) -> 1950000 | L25: =E25*_xlfn.XLOOKUP($C25,$B$14:$B$17,D$14:D$17, 0, 0,1) -> 2052631.6 | M25: =L25-J25 -> 102631.58 | N25: =J25-I25 -> 150000
B26: Customer 4 | C26: GBP | D26: {=_xlfn.XLOOKUP($B26, 'Multi-currency order book'!$B$7:$B$36, 'Multi-currency order book'!D$7:D$36, FEHLER, 0)} -> 0 | E26: {=_xlfn.XLOOKUP($B26, 'Multi-currency order book'!$B$7:$B$36, 'Multi-currency order book'!E$7:E$36, FEHLER, 0)} -> 1298259.1 | H26: Customer 4 | I26: =D26*_xlfn.XLOOKUP($C26,$B$14:$B$17,D$14:D$17, 0, 0,1) -> 0 | J26: =E26*_xlfn.XLOOKUP($C26,$B$14:$B$17,E$14:E$17, 0, 0,1) -> 1754000 | L26: =E26*_xlfn.XLOOKUP($C26,$B$14:$B$17,D$14:D$17, 0, 0,1) -> 1771993.9 | M26: =L26-J26 -> 17993.871 | N26: =J26-I26 -> 1754000
B27: Customer 5 | C27: USD | D27: {=_xlfn.XLOOKUP($B27, 'Multi-currency order book'!$B$7:$B$36, 'Multi-currency order book'!D$7:D$36, FEHLER, 0)} -> 500000 | E27: {=_xlfn.XLOOKUP($B27, 'Multi-currency order book'!$B$7:$B$36, 'Multi-currency order book'!E$7:E$36, FEHLER, 0)} -> 1500000 | H27: Customer 5 | I27: =D27*_xlfn.XLOOKUP($C27,$B$14:$B$17,D$14:D$17, 0, 0,1) -> 500000 | J27: =E27*_xlfn.XLOOKUP($C27,$B$14:$B$17,E$14:E$17, 0, 0,1) -> 1500000 | L27: =E27*_xlfn.XLOOKUP($C27,$B$14:$B$17,D$14:D$17, 0, 0,1) -> 1500000 | M27: =L27-J27 -> 0 | N27: =J27-I27 -> 1000000
B28: Customer 6 | C28: ZAR | D28: {=_xlfn.XLOOKUP($B28, 'Multi-currency order book'!$B$7:$B$36, 'Multi-currency order book'!D$7:D$36, FEHLER, 0)} -> 6617776.5 | E28: {=_xlfn.XLOOKUP($B28, 'Multi-currency order book'!$B$7:$B$36, 'Multi-currency order book'!E$7:E$36, FEHLER, 0)} -> 21517373 | H28: Customer 6 | I28: =D28*_xlfn.XLOOKUP($C28,$B$14:$B$17,D$14:D$17, 0, 0,1) -> 451200 | J28: =E28*_xlfn.XLOOKUP($C28,$B$14:$B$17,E$14:E$17, 0, 0,1) -> 1350000 | L28: =E28*_xlfn.XLOOKUP($C28,$B$14:$B$17,D$14:D$17, 0, 0,1) -> 1467054.5 | M28: =L28-J28 -> 117054.51 | N28: =J28-I28 -> 898800
B29: Customer 7 | C29: ZAR | D29: {=_xlfn.XLOOKUP($B29, 'Multi-currency order book'!$B$7:$B$36, 'Multi-currency order book'!D$7:D$36, FEHLER, 0)} -> 11029627 | E29: {=_xlfn.XLOOKUP($B29, 'Multi-currency order book'!$B$7:$B$36, 'Multi-currency order book'!E$7:E$36, FEHLER, 0)} -> 17532675 | H29: Customer 7 | I29: =D29*_xlfn.XLOOKUP($C29,$B$14:$B$17,D$14:D$17, 0, 0,1) -> 752000 | J29: =E29*_xlfn.XLOOKUP($C29,$B$14:$B$17,E$14:E$17, 0, 0,1) -> 1100000 | L29: =E29*_xlfn.XLOOKUP($C29,$B$14:$B$17,D$14:D$17, 0, 0,1) -> 1195377.7 | M29: =L29-J29 -> 95377.749 | N29: =J29-I29 -> 348000
B30: Customer 8 | C30: RWF | D30: {=_xlfn.XLOOKUP($B30, 'Multi-currency order book'!$B$7:$B$36, 'Multi-currency order book'!D$7:D$36, FEHLER, 0)} -> 0 | E30: {=_xlfn.XLOOKUP($B30, 'Multi-currency order book'!$B$7:$B$36, 'Multi-currency order book'!E$7:E$36, FEHLER, 0)} -> 8.4210526e+08 | H30: Customer 8 | I30: =D30*_xlfn.XLOOKUP($C30,$B$14:$B$17,D$14:D$17, 0, 0,1) -> 0 | J30: =E30*_xlfn.XLOOKUP($C30,$B$14:$B$17,E$14:E$17, 0, 0,1) -> 800000 | L30: =E30*_xlfn.XLOOKUP($C30,$B$14:$B$17,D$14:D$17, 0, 0,1) -> 842105.26 | M30: =L30-J30 -> 42105.263 | N30: =J30-I30 -> 800000
B31: Customer 9 | C31: USD | D31: {=_xlfn.XLOOKUP($B31, 'Multi-currency order book'!$B$7:$B$36, 'Multi-currency order book'!D$7:D$36, FEHLER, 0)} -> 12580 | E31: {=_xlfn.XLOOKUP($B31, 'Multi-currency order book'!$B$7:$B$36, 'Multi-currency order book'!E$7:E$36, FEHLER, 0)} -> 550000 | H31: Customer 9 | I31: =D31*_xlfn.XLOOKUP($C31,$B$14:$B$17,D$14:D$17, 0, 0,1) -> 12580 | J31: =E31*_xlfn.XLOOKUP($C31,$B$14:$B$17,E$14:E$17, 0, 0,1) -> 550000 | L31: =E31*_xlfn.XLOOKUP($C31,$B$14:$B$17,D$14:D$17, 0, 0,1) -> 550000 | M31: =L31-J31 -> 0 | N31: =J31-I31 -> 537420
B32: Customer 10 | C32: GBP | D32: {=_xlfn.XLOOKUP($B32, 'Multi-currency order book'!$B$7:$B$36, 'Multi-currency order book'!D$7:D$36, FEHLER, 0)} -> 128876.84 | E32: {=_xlfn.XLOOKUP($B32, 'Multi-currency order book'!$B$7:$B$36, 'Multi-currency order book'!E$7:E$36, FEHLER, 0)} -> 305320.35 | H32: Customer 10 | I32: =D32*_xlfn.XLOOKUP($C32,$B$14:$B$17,D$14:D$17, 0, 0,1) -> 175904 | J32: =E32*_xlfn.XLOOKUP($C32,$B$14:$B$17,E$14:E$17, 0, 0,1) -> 412500 | L32: =E32*_xlfn.XLOOKUP($C32,$B$14:$B$17,D$14:D$17, 0, 0,1) -> 416731.74 | M32: =L32-J32 -> 4231.74 | N32: =J32-I32 -> 236596
B33: Total | D33: =SUM(D23:D32) -> 1.850555e+09 | E33: =SUM(E23:E32) -> 2.989999e+09 | H33: Total | I33: =SUM(I23:I32) -> 7791684 | J33: =SUM(J23:J32) -> 14716500 | K33: =SUM(K23:K32) -> 0 | L33: =SUM(L23:L32) -> 15394901 | M33: =SUM(M23:M32) -> 678400.66 | N33: =SUM(N23:N32) -> 6924816
I34: =I33/'Multi-currency order book'!D41 -> 0.58959369 | J34: =J33/'Multi-currency order book'!E41 -> 0.79709727

Sheet Sources for Task II >>>

Sheet Multi-currency order book
B2: Multi-Currency Order Book
B5: Customer Order Book
B6: Customer | C6: Currency | D6: 2020 | E6: =D6+1 -> 2021
B7: Customer 1 | C7: ZAR | D7: 30800821 | E7: 51004144
B8: Customer 2 | C8: GBP | D8: 1465308.8 | E8: 1554358.1
B9: Customer 3 | C9: RWF | D9: 1800000000 | E9: 2.0526316e+09
B10: Customer 4 | C10: GBP | D10: 0 | E10: 1298259.1
B11: Customer 5 | C11: USD | D11: 500000 | E11: 1500000
B12: Customer 6 | C12: ZAR | D12: 6617776.5 | E12: 21517373
B13: Customer 7 | C13: ZAR | D13: 11029627 | E13: 17532675
B14: Customer 8 | C14: RWF | D14: 0 | E14: 8.4210526e+08
B15: Customer 9 | C15: USD | D15: 12580 | E15: 550000
B16: Customer 10 | C16: GBP | D16: 128876.84 | E16: 305320.35
B17: Other | C17: USD | D17: 418097 | E17: 426458.94
B18: Other | C18: RWF | D18: 453496000 | E18: 4.0401373e+08
... B36: Other | C36: USD | D36: 20865 | E36: 57608.279
B38: Total | D38: =SUM(D7:D36) -> 2.8658223e+09 | E38: =SUM(E7:E36) -> 3.7012826e+09
B41: Total revenue in USD | D41: 13215345 | E41: 18462615
B42: thereof Other | D42: 5423661 | E42: 3746114.9
